README
setup.cfg
setup.py
bezel/__init__.py
bezel/misc.py
bezel/resources.py
bezel.egg-info/PKG-INFO
bezel.egg-info/SOURCES.txt
bezel.egg-info/dependency_links.txt
bezel.egg-info/requires.txt
bezel.egg-info/top_level.txt
bezel/graphics/__init__.py
bezel/graphics/containers.py
bezel/graphics/display.py
bezel/graphics/scene.py
bezel/graphics/stage.py
bezel/graphics/widget.py
bezel/graphics/widgets/__init__.py
bezel/graphics/widgets/button.py
bezel/graphics/widgets/containers.py
bezel/graphics/widgets/image.py
bezel/graphics/widgets/proportional.py
bezel/graphics/widgets/text.py
bezel/graphics/widgets/tiles/__init__.py
bezel/graphics/widgets/tiles/isometric.py
bezel/graphics/widgets/tiles/tilemap.py
bezel/networking/__init__.py
bezel/networking/client.py
bezel/networking/engine.py
bezel/networking/lobby.py
bezel/networking/lobby_avahi.py
bezel/networking/lobby_bonjour.py
bezel/networking/server.py