Metadata-Version: 1.0
Name: bezel
Version: 1.0dev-r162
Summary: A game development library for Python (graphics with PyGame).
Home-page: http://flowblok.selfip.net:8001/bezel-games/
Author: Peter Ward
Author-email: peteraward@gmail.com
License: UNKNOWN
Platform: UNKNOWN
